gen_coap_service/__init__.py
gen_coap_service/py.typed
gen_coap_service/conf/gen_coap_service.cfg
gen_coap_service/conf/gen_coap_service.logo
gen_coap_service/conf/project.yaml
gen_coap_service/conf/template/template_coapthon.yaml
gen_coap_service/conf/template/template_libcoap.yaml
gen_coap_service/conf/template/template_node_coap.yaml
gen_coap_service/conf/template/coapthon/basic_resources.template
gen_coap_service/conf/template/coapthon/coap_client.template
gen_coap_service/conf/template/coapthon/coap_server.template
gen_coap_service/conf/template/coapthon/logging.template
gen_coap_service/conf/template/libcoap/coap_client/Makefile.template
gen_coap_service/conf/template/libcoap/coap_client/README.template
gen_coap_service/conf/template/libcoap/coap_client/autogen.template
gen_coap_service/conf/template/libcoap/coap_client/configure.template
gen_coap_service/conf/template/libcoap/coap_client/build/editorconfig.template
gen_coap_service/conf/template/libcoap/coap_client/src/Makefile.template
gen_coap_service/conf/template/libcoap/coap_client/src/client_api.template
gen_coap_service/conf/template/libcoap/coap_client/src/main.template
gen_coap_service/conf/template/libcoap/coap_client/src/print_error.template
gen_coap_service/conf/template/libcoap/coap_client/src/print_success.template
gen_coap_service/conf/template/libcoap/coap_client/src/print_usage.template
gen_coap_service/conf/template/libcoap/coap_client/src/print_verbose.template
gen_coap_service/conf/template/libcoap/coap_client/src/process_options.template
gen_coap_service/conf/template/libcoap/coap_client/src/time_handler.template
gen_coap_service/conf/template/libcoap/coap_server/Makefile.template
gen_coap_service/conf/template/libcoap/coap_server/README.template
gen_coap_service/conf/template/libcoap/coap_server/autogen.template
gen_coap_service/conf/template/libcoap/coap_server/configure.template
gen_coap_service/conf/template/libcoap/coap_server/build/editorconfig.template
gen_coap_service-1.1.5.dist-info/LICENSE
gen_coap_service-1.1.5.dist-info/METADATA
gen_coap_service-1.1.5.dist-info/WHEEL
gen_coap_service-1.1.5.dist-info/top_level.txt
gen_coap_service-1.1.5.dist-info/RECORD
